<?xml version="1.0" encoding="UTF-8"?>
<tv generator-info-name="prime_acontra_plus">
  <channel id="acontra+ CINE">
    <display-name>acontra+ CINE</display-name>
  </channel>
  <programme start="20260404130600 +0200" stop="20260404150600 +0200" channel="acontra+ CINE">
    <title lang="es">Ms. 45 (1981)</title>
    <desc lang="es">Una joven sordomuda que ha sido violada recorre las calles de Nueva York en busca de venganza. | Edad: 16+</desc>
    <icon src="https://m.media-amazon.com/images/I/A1wWBblTgjL._UR1920,1080_FMpng_.jpg"/>
  </programme>
  <programme start="20260404150600 +0200" stop="20260404165500 +0200" channel="acontra+ CINE">
    <title lang="es">Las aventuras de Picasso (2013)</title>
    <desc lang="es">En Madrid, Pablo Picasso se convirtió en pintor, pero se fue a París, donde vivió en la pobreza. | Edad: 7+</desc>
    <icon src="https://m.media-amazon.com/images/I/81qm55QU0oL._UR1920,1080_FMpng_.jpg"/>
  </programme>
  <programme start="20260404165500 +0200" stop="20260404184200 +0200" channel="acontra+ CINE">
    <title lang="es">Culpable sin rostro (conducta indecorosa) (2018)</title>
    <desc lang="es">Un soldado británico trasladado a la India contra su voluntad comienza a rebelarse. | Edad: 18+</desc>
    <icon src="https://m.media-amazon.com/images/I/91kPrF3vm8L._UR1920,1080_FMpng_.jpg"/>
  </programme>
  <programme start="20260404184200 +0200" stop="20260404202100 +0200" channel="acontra+ CINE">
    <title lang="es">El último gran día (2009)</title>
    <desc lang="es">Un temible solitario prepara su propio funeral y piensa asistir a él para revelárselo a todos. | Edad: 13+</desc>
    <icon src="https://m.media-amazon.com/images/G/01/LCXO_Station_Logos/16x9Cover/acontra_CINE_16x9._UR1920,1080_FMpng_.png"/>
  </programme>
  <programme start="20260404202100 +0200" stop="20260404221800 +0200" channel="acontra+ CINE">
    <title lang="es">La tierra de los hijos</title>
    <desc lang="es">El final de la civilización ha llegado. Un padre y su hijo se encuentran entre los supervivientes. | Edad: 16+</desc>
    <icon src="https://m.media-amazon.com/images/I/81UTrjFMl3L._UR1920,1080_FMpng_.jpg"/>
  </programme>
  <programme start="20260404221800 +0200" stop="20260405000000 +0200" channel="acontra+ CINE">
    <title lang="es">Los limoneros (2008)</title>
    <desc lang="es">Salma, una viuda palestina, defiende sus limoneros frente a las fuerzas de seguridad israelíes. | Edad: 13+</desc>
    <icon src="https://m.media-amazon.com/images/I/818VZluvhoL._UR1920,1080_FMpng_.jpg"/>
  </programme>
</tv>